holiday_chn/__init__.py
holiday_chn/config.py
holiday_chn/holiday_chn.py
holiday_chn-1.2024.3.dist-info/METADATA
holiday_chn-1.2024.3.dist-info/WHEEL
holiday_chn-1.2024.3.dist-info/top_level.txt
holiday_chn-1.2024.3.dist-info/RECORD
