Metadata-Version: 2.1
Name: holiday-chn
Version: 1.2024.3
Summary: This package provides judgment on Chinese holidays and outputs the dates of all holidays.By using it, one can determine whether a certain date is a holiday and obtain the working days or holidays of a certain year.
Author: lytcreate
Author-email: lytcreate <lytcreate@163.com>
License: ZPL 2.1
Classifier: Programming Language :: Python :: 3
Classifier: License :: OSI Approved :: MIT License
Requires-Python: >=3.0
